pyfelicita/Felicita.py
pyfelicita/__init__.py
pyfelicita/constants.py
pyfelicita-0.1.15.dist-info/licenses/LICENSE
pyfelicita-0.1.15.dist-info/METADATA
pyfelicita-0.1.15.dist-info/WHEEL
pyfelicita-0.1.15.dist-info/top_level.txt
pyfelicita-0.1.15.dist-info/RECORD
