Metadata-Version: 2.4
Name: pyfelicita
Version: 0.1.15
Summary: A Bluetooth scale integration for coffee machines
Home-page: https://github.com/kevinstampe/pyfelicita
Author: Kevin Guldager Stampe
Author-email: kevinstampe@gmail.com
License: MIT
Classifier: Programming Language :: Python :: 3
Classifier: License :: OSI Approved :: MIT License
Classifier: Operating System :: OS Independent
Requires-Python: >=3.7
License-File: LICENSE
Requires-Dist: bleak
Dynamic: author
Dynamic: author-email
Dynamic: classifier
Dynamic: description
Dynamic: description-content-type
Dynamic: home-page
Dynamic: license
Dynamic: license-file
Dynamic: requires-dist
Dynamic: requires-python
Dynamic: summary
